{
  "FERTILIZERS": [
    {
      "experiment_ID": "Bustos-Korts2013_2010",
      "fertiliz_app_name": null,
      "fertilization_date": null,
      "fertilizer_material": null,
      "fertilizer_total_amount": "600",
      "N_in_applied_fertilizer": "150",
      "phosphorus_applied_fert": "300",
      "fertilizer_K_applied": 150,
      "fertilizer_applic_notes": "fertilized at sowing"
    },
    {
      "experiment_ID": "Bustos-Korts2013_2010",
      "fertiliz_app_name": null,
      "fertilization_date": null,
      "fertilizer_material": null,
      "fertilizer_total_amount": "150",
      "N_in_applied_fertilizer": "150",
      "phosphorus_applied_fert": null,
      "fertilizer_K_applied": null,
      "fertilizer_applic_notes": "applied at tillering"
    }
  ]
}
