{
  "FERTILIZERS": [
    {
      "experiment_ID": "Kimball1999_1996",
      "fertiliz_app_name": "High N",
      "fertilization_date": null,
      "fertilizer_material": "FE001",
      "fertilizer_total_amount": "350",
      "N_in_applied_fertilizer": "350",
      "phosphorus_applied_fert": null,
      "fertilizer_K_applied": null,
      "fertilizer_applic_notes": null
    },
    {
      "experiment_ID": "Kimball1999_1996",
      "fertiliz_app_name": "High N",
      "fertilization_date": null,
      "fertilizer_material": "FE001",
      "fertilizer_total_amount": "33",
      "N_in_applied_fertilizer": "33",
      "phosphorus_applied_fert": null,
      "fertilizer_K_applied": null,
      "fertilizer_applic_notes": "from the irrigation water itself"
    },
    {
      "experiment_ID": "Kimball1999_1996",
      "fertiliz_app_name": "Low N",
      "fertilization_date": null,
      "fertilizer_material": "FE001",
      "fertilizer_total_amount": "70",
      "N_in_applied_fertilizer": "70",
      "phosphorus_applied_fert": null,
      "fertilizer_K_applied": null,
      "fertilizer_applic_notes": null
    },
    {
      "experiment_ID": "Kimball1999_1996",
      "fertiliz_app_name": "Low N",
      "fertilization_date": null,
      "fertilizer_material": "FE001",
      "fertilizer_total_amount": "30",
      "N_in_applied_fertilizer": "30",
      "phosphorus_applied_fert": null,
      "fertilizer_K_applied": null,
      "fertilizer_applic_notes": "from the irrigation water itself"
    }
  ]
}
