{
  "FERTILIZERS": [
    {
      "experiment_ID": "Li2014_1981",
      "fertiliz_app_name": "N0",
      "fertilization_date": "1981-09-20",
      "fertilizer_material": null,
      "fertilizer_total_amount": "0",
      "N_in_applied_fertilizer": null,
      "phosphorus_applied_fert": null,
      "fertilizer_K_applied": null,
      "fertilizer_applic_notes": null
    },
    {
      "experiment_ID": "Li2014_1981",
      "fertiliz_app_name": "N90",
      "fertilization_date": "1981-09-20",
      "fertilizer_material": "FE005",
      "fertilizer_total_amount": "90",
      "N_in_applied_fertilizer": "90",
      "phosphorus_applied_fert": null,
      "fertilizer_K_applied": null,
      "fertilizer_applic_notes": null
    },
    {
      "experiment_ID": "Li2014_1981",
      "fertiliz_app_name": "SN90",
      "fertilization_date": "1981-09-20",
      "fertilizer_material": "FE005",
      "fertilizer_total_amount": "90",
      "N_in_applied_fertilizer": "90",
      "phosphorus_applied_fert": null,
      "fertilizer_K_applied": null,
      "fertilizer_applic_notes": null
    },
    {
      "experiment_ID": "Li2014_1981",
      "fertiliz_app_name": "SN90",
      "fertilization_date": "1981-07-02",
      "fertilizer_material": null,
      "fertilizer_total_amount": "30",
      "N_in_applied_fertilizer": "30",
      "phosphorus_applied_fert": null,
      "fertilizer_K_applied": null,
      "fertilizer_applic_notes": "straw residue"
    },
    {
      "experiment_ID": "Li2014_1981",
      "fertiliz_app_name": "MN90",
      "fertilization_date": "1981-09-20",
      "fertilizer_material": "FE005",
      "fertilizer_total_amount": "90",
      "N_in_applied_fertilizer": "90",
      "phosphorus_applied_fert": null,
      "fertilizer_K_applied": null,
      "fertilizer_applic_notes": null
    },
    {
      "experiment_ID": "Li2014_1981",
      "fertiliz_app_name": "MN90",
      "fertilization_date": "1981-09-20",
      "fertilizer_material": null,
      "fertilizer_total_amount": "40",
      "N_in_applied_fertilizer": "40",
      "phosphorus_applied_fert": null,
      "fertilizer_K_applied": null,
      "fertilizer_applic_notes": null
    }
  ]
}
