{
  "FERTILIZERS": [
    {
      "experiment_ID": "Dueri2022_2013_Leeston",
      "fertilizer_level_name": null,
      "fertilization_date": null,
      "fertilizer_material": null,
      "fertilizer_total_amount": "138",
      "N_in_applied_fertilizer": "138",
      "phosphorus_applied_fert": null,
      "fertilizer_K_applied": null,
      "fertilizer_applic_notes": null
    },
    {
      "experiment_ID": "Dueri2022_2014_Leeston",
      "fertilizer_level_name": null,
      "fertilization_date": null,
      "fertilizer_material": null,
      "fertilizer_total_amount": "122",
      "N_in_applied_fertilizer": "122",
      "phosphorus_applied_fert": null,
      "fertilizer_K_applied": null,
      "fertilizer_applic_notes": null
    },
    {
      "experiment_ID": "Dueri2022_2015_Leeston",
      "fertilizer_level_name": null,
      "fertilization_date": null,
      "fertilizer_material": null,
      "fertilizer_total_amount": "188",
      "N_in_applied_fertilizer": "188",
      "phosphorus_applied_fert": null,
      "fertilizer_K_applied": null,
      "fertilizer_applic_notes": null
    },
    {
      "experiment_ID": "Dueri2022_2016_Wakanui",
      "fertilizer_level_name": null,
      "fertilization_date": null,
      "fertilizer_material": null,
      "fertilizer_total_amount": "284",
      "N_in_applied_fertilizer": "284",
      "phosphorus_applied_fert": null,
      "fertilizer_K_applied": null,
      "fertilizer_applic_notes": null
    },
    {
      "experiment_ID": "Dueri2022_2017_Wakanui",
      "fertilizer_level_name": null,
      "fertilization_date": null,
      "fertilizer_material": null,
      "fertilizer_total_amount": "258",
      "N_in_applied_fertilizer": "258",
      "phosphorus_applied_fert": null,
      "fertilizer_K_applied": null,
      "fertilizer_applic_notes": null
    },
    {
      "experiment_ID": "Dueri2022_2018_Wakanui",
      "fertilizer_level_name": null,
      "fertilization_date": null,
      "fertilizer_material": null,
      "fertilizer_total_amount": "270",
      "N_in_applied_fertilizer": "270",
      "phosphorus_applied_fert": null,
      "fertilizer_K_applied": null,
      "fertilizer_applic_notes": null
    }
  ]
}
